smhi_weather/__init__.py
smhi_weather/main.py
smhi_weather-0.1.2.dist-info/LICENSE
smhi_weather-0.1.2.dist-info/METADATA
smhi_weather-0.1.2.dist-info/WHEEL
smhi_weather-0.1.2.dist-info/top_level.txt
smhi_weather-0.1.2.dist-info/RECORD
